README.md
setup.py
skewdi/skewdi.py
skewdi.egg-info/PKG-INFO
skewdi.egg-info/SOURCES.txt
skewdi.egg-info/dependency_links.txt
skewdi.egg-info/requires.txt
skewdi.egg-info/top_level.txt