Metadata-Version: 2.1
Name: skewdi
Version: 1.0.12
Summary: Fetch Website Content
Home-page: UNKNOWN
Author: Sam
Author-email: samprits5@gmail.com
License: MIT
Platform: UNKNOWN
Classifier: License :: OSI Approved :: MIT License
Classifier: Programming Language :: Python
Classifier: Programming Language :: Python :: 3
